herbie/__init__.py
herbie/_debug.py
herbie/accessors.py
herbie/archive.py
herbie/hrrr_zarr.py
herbie/misc.py
herbie/tools.py
herbie/models/__init__.py
herbie/models/gfs.py
herbie/models/gfs_wave.py
herbie/models/hrrr.py
herbie/models/hrrrak.py
herbie/models/navgem.py
herbie/models/nbm.py
herbie/models/rap.py
herbie/models/rrfs.py
hrrrb/__init__.py
hrrrb/accessors.py
hrrrb/archive.py
hrrrb/plots.py
hrrrb/tools.py
hrrrb-0.0.6.dist-info/LICENSE
hrrrb-0.0.6.dist-info/METADATA
hrrrb-0.0.6.dist-info/WHEEL
hrrrb-0.0.6.dist-info/top_level.txt
hrrrb-0.0.6.dist-info/RECORD
