Metadata-Version: 2.1
Name: hrrrb
Version: 0.0.6
Summary: Download model data (HRRR, RAP, GFS, NBM, etc.) from NOMADS, NOAA's Big Data Program partners (Amazon, Google, Microsoft), and the University of Utah Pando Archive System.
Home-page: UNKNOWN
Author: Brian K. Blaylock
Author-email: blaylockbk@gmail.com
License: MIT
Project-URL: Source Code, https://github.com/blaylockbk/Herbie
Project-URL: Documentation, https://blaylockbk.github.io/Herbie/_build/html/
Keywords: xarray,meteorology,weather,HRRR,numerical weather prediction,forecast
Platform: UNKNOWN
Classifier: Development Status :: 4 - Beta
Classifier: License :: OSI Approved :: MIT License
Classifier: Intended Audience :: Developers
Classifier: Intended Audience :: Education
Classifier: Intended Audience :: Science/Research
Classifier: Natural Language :: English
Classifier: Programming Language :: Python
Classifier: Topic :: Scientific/Engineering :: Atmospheric Science
Requires-Python: >=3.8
License-File: LICENSE
Requires-Dist: numpy
Requires-Dist: pandas
Requires-Dist: xarray
Requires-Dist: cfgrib
